Workbook

Sheet Parametros
A1: Inventario GEI (ejemplo) y parámetros de conversión
A2: Datos de ejemplo (sintéticos) con fines didácticos. Celdas azules sobre fondo crema = entradas editables; el resto son fórmulas.
A4: Horizonte GWP (100 o 20 años) | B4: 100
A6: Gas | B6: GWP-100 | C6: GWP-20 | D6: GWP aplicado | E6: Fuente
A7: CO₂ | B7: 1 | C7: 1 | D7: =IF($B$4=20,C7,B7) -> 1 | E7: IPCC AR6 WGI, cap. 7 (tabla 7.15)
A8: CH₄ fósil | B8: 29.8 | C8: 82.5 | D8: =IF($B$4=20,C8,B8) -> 29.8 | E8: IPCC AR6 WGI, cap. 7 (tabla 7.15)
A9: N₂O | B9: 273 | C9: 273 | D9: =IF($B$4=20,C9,B9) -> 273 | E9: IPCC AR6 WGI, cap. 7 (tabla 7.15)
A11: Valores de GWP de AR6; verificar versión vigente del inventario que se reporte (el marco exige consistencia).

Sheet Inventario
A1: Inventario por fuente (datos de ejemplo)
A2: Datos de ejemplo (sintéticos) con fines didácticos. Celdas azules sobre fondo crema = entradas editables; el resto son fórmulas.
A4: Fuente | B4: Alcance | C4: CO₂ (t/año) | D4: CH₄ (t/año) | E4: N₂O (t/año) | F4: Total (tCO₂e) | G4: Aporte CH₄ (tCO₂e) | H4: % del total
A5: Combustión en turbinas y calderas | B5: 1 | C5: 95000 | D5: 12 | E5: 2 | F5: =C5*Parametros!$D$7+D5*Parametros!$D$8+E5*Parametros!$D$9 -> 95903.6 | G5: =D5*Parametros!$D$8 -> 357.6 | H5: =F5/$F$13 -> 0.28940533
A6: Antorcha (flare) | B6: 1 | C6: 40000 | D6: 35 | E6: 1 | F6: =C6*Parametros!$D$7+D6*Parametros!$D$8+E6*Parametros!$D$9 -> 41316 | G6: =D6*Parametros!$D$8 -> 1043 | H6: =F6/$F$13 -> 0.12467801
A7: Venteo de gas | B7: 1 | C7: 2500 | D7: 1800 | E7: 0 | F7: =C7*Parametros!$D$7+D7*Parametros!$D$8+E7*Parametros!$D$9 -> 56140 | G7: =D7*Parametros!$D$8 -> 53640 | H7: =F7/$F$13 -> 0.16941194
A8: Emisiones fugitivas (válvulas, bridas) | B8: 1 | C8: 0 | D8: 950 | E8: 0 | F8: =C8*Parametros!$D$7+D8*Parametros!$D$8+E8*Parametros!$D$9 -> 28310 | G8: =D8*Parametros!$D$8 -> 28310 | H8: =F8/$F$13 -> 0.085430211
A9: Controladores neumáticos | B9: 1 | C9: 0 | D9: 600 | E9: 0 | F9: =C9*Parametros!$D$7+D9*Parametros!$D$8+E9*Parametros!$D$9 -> 17880 | G9: =D9*Parametros!$D$8 -> 17880 | H9: =F9/$F$13 -> 0.053955923
A10: Compresores sellos | B10: 1 | C10: 0 | D10: 450 | E10: 0 | F10: =C10*Parametros!$D$7+D10*Parametros!$D$8+E10*Parametros!$D$9 -> 13410 | G10: =D10*Parametros!$D$8 -> 13410 | H10: =F10/$F$13 -> 0.040466942
A11: Electricidad comprada | B11: 2 | C11: 60000 | D11: 0 | E11: 0 | F11: =C11*Parametros!$D$7+D11*Parametros!$D$8+E11*Parametros!$D$9 -> 60000 | G11: =D11*Parametros!$D$8 -> 0 | H11: =F11/$F$13 -> 0.18106014
A12: Transporte de insumos | B12: 3 | C12: 18000 | D12: 5 | E12: 1 | F12: =C12*Parametros!$D$7+D12*Parametros!$D$8+E12*Parametros!$D$9 -> 18422 | G12: =D12*Parametros!$D$8 -> 149 | H12: =F12/$F$13 -> 0.055591499
A13: TOTAL | C13: =SUM(C5:C12) -> 215500 | D13: =SUM(D5:D12) -> 3852 | E13: =SUM(E5:E12) -> 4 | F13: =SUM(F5:F12) -> 331381.6 | G13: =SUM(G5:G12) -> 114789.6
A15: Por alcance
A16: Alcance | B16: tCO₂e | C16: %
A17: Alcance 1 | B17: =SUMIF($B$5:$B$12,1,$F$5:$F$12) -> 252959.6 | C17: =B17/$F$13 -> 0.76334836
A18: Alcance 2 | B18: =SUMIF($B$5:$B$12,2,$F$5:$F$12) -> 60000 | C18: =B18/$F$13 -> 0.18106014
A19: Alcance 3 | B19: =SUMIF($B$5:$B$12,3,$F$5:$F$12) -> 18422 | C19: =B19/$F$13 -> 0.055591499
A21: Peso del metano en el total | B21: =G13/F13 -> 0.34639702
A22: Cambiá el horizonte en Parametros!B4 (100 → 20) y mirá cuánto sube.

Sheet MACC
A1: Curva de costo marginal de abatimiento (MACC) – ejemplo
A2: Datos de ejemplo (sintéticos) con fines didácticos. Celdas azules sobre fondo crema = entradas editables; el resto son fórmulas.
A4: Precio del carbono (USD/tCO₂e) | B4: 50
A5: Precio del gas (USD/MMBtu) | B5: 3
A6: Tasa de descuento | B6: 0.1
A7: MMBtu por t de CH₄ | B7: 52
A9: Medida | B9: CH₄ evitado (t/año) | C9: CO₂ evitado (t/año) | D9: Gas ahorrado (MMBtu/año) | E9: CAPEX (USD) | F9: Vida (años) | G9: Opex (USD/año) | H9: Abatimiento (tCO₂e/año) | I9: Costo neto (USD/tCO₂e) | J9: ¿Viable al precio de carbono? | K9: Orden
A10: Recuperación de gas de venteo a gasoducto | B10: 1500 | C10: 0 | D10: =B10*$B$7 -> 78000 | E10: 1200000 | F10: 10 | G10: 60000 | H10: =B10*Parametros!$D$8+C10 -> 44700 | I10: =(PMT($B$6,F10,-E10)+G10-D10*$B$5)/H10 -> 0.47638644 | J10: =IF(I10<=$B$4,"Sí","No") -> Sí | K10: =RANK(I10,$I$10:$I$17,1)+COUNTIF($I$10:I10,I10)-1 -> 3
A11: Reemplazo de controladores neumáticos | B11: 550 | C11: 0 | D11: =B11*$B$7 -> 28600 | E11: 350000 | F11: 10 | G11: 5000 | H11: =B11*Parametros!$D$8+C11 -> 16390 | I11: =(PMT($B$6,F11,-E11)+G11-D11*$B$5)/H11 -> -1.4544913 | J11: =IF(I11<=$B$4,"Sí","No") -> Sí | K11: =RANK(I11,$I$10:$I$17,1)+COUNTIF($I$10:I11,I11)-1 -> 1
A12: Programa LDAR (detección y reparación de fugas) | B12: 700 | C12: 0 | D12: =B12*$B$7 -> 36400 | E12: 250000 | F12: 5 | G12: 150000 | H12: =B12*Parametros!$D$8+C12 -> 20860 | I12: =(PMT($B$6,F12,-E12)+G12-D12*$B$5)/H12 -> 5.1174195 | J12: =IF(I12<=$B$4,"Sí","No") -> Sí | K12: =RANK(I12,$I$10:$I$17,1)+COUNTIF($I$10:I12,I12)-1 -> 5
A13: Recuperadora de vapores en tanques | B13: 300 | C13: 0 | D13: =B13*$B$7 -> 15600 | E13: 420000 | F13: 10 | G13: 30000 | H13: =B13*Parametros!$D$8+C13 -> 8940 | I13: =(PMT($B$6,F13,-E13)+G13-D13*$B$5)/H13 -> 5.7665622 | J13: =IF(I13<=$B$4,"Sí","No") -> Sí | K13: =RANK(I13,$I$10:$I$17,1)+COUNTIF($I$10:I13,I13)-1 -> 6
A14: Cambio de sellos de compresor | B14: 380 | C14: 0 | D14: =B14*$B$7 -> 19760 | E14: 300000 | F14: 8 | G14: 10000 | H14: =B14*Parametros!$D$8+C14 -> 11324 | I14: =(PMT($B$6,F14,-E14)+G14-D14*$B$5)/H14 -> 0.61402378 | J14: =IF(I14<=$B$4,"Sí","No") -> Sí | K14: =RANK(I14,$I$10:$I$17,1)+COUNTIF($I$10:I14,I14)-1 -> 4
A15: Eficiencia en turbinas (recuperación de calor) | B15: 0 | C15: 12000 | D15: 180000 | E15: 3500000 | F15: 15 | G15: 80000 | H15: =B15*Parametros!$D$8+C15 -> 12000 | I15: =(PMT($B$6,F15,-E15)+G15-D15*$B$5)/H15 -> 0.013184925 | J15: =IF(I15<=$B$4,"Sí","No") -> Sí | K15: =RANK(I15,$I$10:$I$17,1)+COUNTIF($I$10:I15,I15)-1 -> 2
A16: Electrificación con energía renovable | B16: 0 | C16: 50000 | D16: 0 | E16: 20000000 | F16: 20 | G16: 250000 | H16: =B16*Parametros!$D$8+C16 -> 50000 | I16: =(PMT($B$6,F16,-E16)+G16-D16*$B$5)/H16 -> 51.98385 | J16: =IF(I16<=$B$4,"Sí","No") -> No | K16: =RANK(I16,$I$10:$I$17,1)+COUNTIF($I$10:I16,I16)-1 -> 8
A17: Reducción de antorcha (gas a uso) | B17: 20 | C17: 8000 | D17: =B17*$B$7 -> 1040 | E17: 800000 | F17: 10 | G17: 40000 | H17: =B17*Parametros!$D$8+C17 -> 8596 | I17: =(PMT($B$6,F17,-E17)+G17-D17*$B$5)/H17 -> 19.436519 | J17: =IF(I17<=$B$4,"Sí","No") -> Sí | K17: =RANK(I17,$I$10:$I$17,1)+COUNTIF($I$10:I17,I17)-1 -> 7
A19: Curva ordenada (menor a mayor costo)
A20: Orden | B20: Medida | C20: Abatimiento (tCO₂e/año) | D20: Abatimiento acumulado | E20: Costo neto (USD/tCO₂e)
A21: 1 | B21: =INDEX($A$10:$A$17,MATCH(A21,$K$10:$K$17,0)) -> Reemplazo de controladores neumáticos | C21: =INDEX($H$10:$H$17,MATCH(A21,$K$10:$K$17,0)) -> 16390 | D21: =SUM($C$21:C21) -> 16390 | E21: =INDEX($I$10:$I$17,MATCH(A21,$K$10:$K$17,0)) -> -1.4544913
A22: 2 | B22: =INDEX($A$10:$A$17,MATCH(A22,$K$10:$K$17,0)) -> Eficiencia en turbinas (recuperación de calor) | C22: =INDEX($H$10:$H$17,MATCH(A22,$K$10:$K$17,0)) -> 12000 | D22: =SUM($C$21:C22) -> 28390 | E22: =INDEX($I$10:$I$17,MATCH(A22,$K$10:$K$17,0)) -> 0.013184925
A23: 3 | B23: =INDEX($A$10:$A$17,MATCH(A23,$K$10:$K$17,0)) -> Recuperación de gas de venteo a gasoducto | C23: =INDEX($H$10:$H$17,MATCH(A23,$K$10:$K$17,0)) -> 44700 | D23: =SUM($C$21:C23) -> 73090 | E23: =INDEX($I$10:$I$17,MATCH(A23,$K$10:$K$17,0)) -> 0.47638644
A24: 4 | B24: =INDEX($A$10:$A$17,MATCH(A24,$K$10:$K$17,0)) -> Cambio de sellos de compresor | C24: =INDEX($H$10:$H$17,MATCH(A24,$K$10:$K$17,0)) -> 11324 | D24: =SUM($C$21:C24) -> 84414 | E24: =INDEX($I$10:$I$17,MATCH(A24,$K$10:$K$17,0)) -> 0.61402378
A25: 5 | B25: =INDEX($A$10:$A$17,MATCH(A25,$K$10:$K$17,0)) -> Programa LDAR (detección y reparación de fugas) | C25: =INDEX($H$10:$H$17,MATCH(A25,$K$10:$K$17,0)) -> 20860 | D25: =SUM($C$21:C25) -> 105274 | E25: =INDEX($I$10:$I$17,MATCH(A25,$K$10:$K$17,0)) -> 5.1174195
A26: 6 | B26: =INDEX($A$10:$A$17,MATCH(A26,$K$10:$K$17,0)) -> Recuperadora de vapores en tanques | C26: =INDEX($H$10:$H$17,MATCH(A26,$K$10:$K$17,0)) -> 8940 | D26: =SUM($C$21:C26) -> 114214 | E26: =INDEX($I$10:$I$17,MATCH(A26,$K$10:$K$17,0)) -> 5.7665622
A27: 7 | B27: =INDEX($A$10:$A$17,MATCH(A27,$K$10:$K$17,0)) -> Reducción de antorcha (gas a uso) | C27: =INDEX($H$10:$H$17,MATCH(A27,$K$10:$K$17,0)) -> 8596 | D27: =SUM($C$21:C27) -> 122810 | E27: =INDEX($I$10:$I$17,MATCH(A27,$K$10:$K$17,0)) -> 19.436519
A28: 8 | B28: =INDEX($A$10:$A$17,MATCH(A28,$K$10:$K$17,0)) -> Electrificación con energía renovable | C28: =INDEX($H$10:$H$17,MATCH(A28,$K$10:$K$17,0)) -> 50000 | D28: =SUM($C$21:C28) -> 172810 | E28: =INDEX($I$10:$I$17,MATCH(A28,$K$10:$K$17,0)) -> 51.98385
A30: Abatimiento viable (tCO₂e/año) | C30: =SUMIF($J$10:$J$17,"Sí",$H$10:$H$17) -> 122810
A31: Costo negativo = la medida se paga sola con el gas que ahorra. Datos de ejemplo: no representan ninguna operación real.
