Workbook

Sheet Parametros
A1: Pozo de ejemplo: flujo de caja mensual a 120 meses
A2: Datos de ejemplo (sintéticos) con fines didácticos. Celdas azules sobre fondo crema = entradas editables; el resto son fórmulas.
A4: Parámetro | B4: Valor | C4: Unidad
A5: Caudal inicial qi | B5: 900 | C5: bbl/d
A6: Declinación Di (armónica, b = 1) | B6: 0.7 | C6: 1/año
A7: Precio del crudo | B7: 65 | C7: USD/bbl
A8: Regalías | B8: 0.12 | C8: fracción
A9: Opex variable | B9: 8 | C9: USD/bbl
A10: Opex fijo | B10: 8000 | C10: USD/mes
A11: CAPEX | B11: 9000000 | C11: USD
A12: Tasa de descuento | B12: 0.1 | C12: anual
A13: Tasa de impuesto a las ganancias | B13: 0 | C13: fracción
A14: Meses de depreciación lineal | B14: 120 | C14: meses
A16: Con impuesto en cero, el resultado coincide con el laboratorio del curso (antes de impuestos). Poné 0,35 para ver el efecto de un impuesto de ejemplo.

Sheet Flujo
A1: Flujo de caja mensual
A2: Datos de ejemplo (sintéticos) con fines didácticos. Celdas azules sobre fondo crema = entradas editables; el resto son fórmulas.
A4: Mes | B4: Tiempo (años) | C4: q (bbl/d) | D4: Volumen (bbl) | E4: Ingreso neto (USD) | F4: Opex (USD) | G4: Depreciación (USD) | H4: Impuesto (USD) | I4: Flujo de caja (USD) | J4: Flujo descontado (USD) | K4: Acumulado (USD)
A5: 0 | B5: =0 -> 0 | I5: =-Parametros!B11 -> -9000000 | J5: =I5 -> -9000000 | K5: =I5 -> -9000000
A6: 1 | B6: =A6/12 -> 0.083333333 | C6: =Parametros!$B$5/(1+Parametros!$B$6*B6) -> 850.3937 | D6: =C6*30.4 -> 25851.969 | E6: =D6*Parametros!$B$7*(1-Parametros!$B$8) -> 1478732.6 | F6: =D6*Parametros!$B$9+Parametros!$B$10 -> 214815.75 | G6: =Parametros!$B$11/Parametros!$B$14 -> 75000 | H6: =MAX(0,E6-F6-G6)*Parametros!$B$13 -> 0 | I6: =E6-F6-H6 -> 1263916.9 | J6: =I6/(1+Parametros!$B$12)^B6 -> 1253917.9 | K6: =K5+I6 -> -7736083.1
A7: 2 | B7: =A7/12 -> 0.16666667 | C7: =Parametros!$B$5/(1+Parametros!$B$6*B7) -> 805.97015 | D7: =C7*30.4 -> 24501.493 | E7: =D7*Parametros!$B$7*(1-Parametros!$B$8) -> 1401485.4 | F7: =D7*Parametros!$B$9+Parametros!$B$10 -> 204011.94 | G7: =Parametros!$B$11/Parametros!$B$14 -> 75000 | H7: =MAX(0,E7-F7-G7)*Parametros!$B$13 -> 0 | I7: =E7-F7-H7 -> 1197473.4 | J7: =I7/(1+Parametros!$B$12)^B7 -> 1178601.8 | K7: =K6+I7 -> -6538609.7
A8: 3 | B8: =A8/12 -> 0.25 | C8: =Parametros!$B$5/(1+Parametros!$B$6*B8) -> 765.95745 | D8: =C8*30.4 -> 23285.106 | E8: =D8*Parametros!$B$7*(1-Parametros!$B$8) -> 1331908.1 | F8: =D8*Parametros!$B$9+Parametros!$B$10 -> 194280.85 | G8: =Parametros!$B$11/Parametros!$B$14 -> 75000 | H8: =MAX(0,E8-F8-G8)*Parametros!$B$13 -> 0 | I8: =E8-F8-H8 -> 1137627.2 | J8: =I8/(1+Parametros!$B$12)^B8 -> 1110840.8 | K8: =K7+I8 -> -5400982.5
A9: 4 | B9: =A9/12 -> 0.33333333 | C9: =Parametros!$B$5/(1+Parametros!$B$6*B9) -> 729.72973 | D9: =C9*30.4 -> 22183.784 | E9: =D9*Parametros!$B$7*(1-Parametros!$B$8) -> 1268912.4 | F9: =D9*Parametros!$B$9+Parametros!$B$10 -> 185470.27 | G9: =Parametros!$B$11/Parametros!$B$14 -> 75000 | H9: =MAX(0,E9-F9-G9)*Parametros!$B$13 -> 0 | I9: =E9-F9-H9 -> 1083442.2 | J9: =I9/(1+Parametros!$B$12)^B9 -> 1049562.2 | K9: =K8+I9 -> -4317540.3
A10: 5 | B10: =A10/12 -> 0.41666667 | C10: =Parametros!$B$5/(1+Parametros!$B$6*B10) -> 696.77419 | D10: =C10*30.4 -> 21181.935 | E10: =D10*Parametros!$B$7*(1-Parametros!$B$8) -> 1211606.7 | F10: =D10*Parametros!$B$9+Parametros!$B$10 -> 177455.48 | G10: =Parametros!$B$11/Parametros!$B$14 -> 75000 | H10: =MAX(0,E10-F10-G10)*Parametros!$B$13 -> 0 | I10: =E10-F10-H10 -> 1034151.2 | J10: =I10/(1+Parametros!$B$12)^B10 -> 993887.2 | K10: =K9+I10 -> -3283389.1
A11: 6 | B11: =A11/12 -> 0.5 | C11: =Parametros!$B$5/(1+Parametros!$B$6*B11) -> 666.66667 | D11: =C11*30.4 -> 20266.667 | E11: =D11*Parametros!$B$7*(1-Parametros!$B$8) -> 1159253.3 | F11: =D11*Parametros!$B$9+Parametros!$B$10 -> 170133.33 | G11: =Parametros!$B$11/Parametros!$B$14 -> 75000 | H11: =MAX(0,E11-F11-G11)*Parametros!$B$13 -> 0 | I11: =E11-F11-H11 -> 989120 | J11: =I11/(1+Parametros!$B$12)^B11 -> 943088.92 | K11: =K10+I11 -> -2294269.1
A12: 7 | B12: =A12/12 -> 0.58333333 | C12: =Parametros!$B$5/(1+Parametros!$B$6*B12) -> 639.05325 | D12: =C12*30.4 -> 19427.219 | E12: =D12*Parametros!$B$7*(1-Parametros!$B$8) -> 1111236.9 | F12: =D12*Parametros!$B$9+Parametros!$B$10 -> 163417.75 | G12: =Parametros!$B$11/Parametros!$B$14 -> 75000 | H12: =MAX(0,E12-F12-G12)*Parametros!$B$13 -> 0 | I12: =E12-F12-H12 -> 947819.17 | J12: =I12/(1+Parametros!$B$12)^B12 -> 896560.82 | K12: =K11+I12 -> -1346449.9
A13: 8 | B13: =A13/12 -> 0.66666667 | C13: =Parametros!$B$5/(1+Parametros!$B$6*B13) -> 613.63636 | D13: =C13*30.4 -> 18654.545 | E13: =D13*Parametros!$B$7*(1-Parametros!$B$8) -> 1067040 | F13: =D13*Parametros!$B$9+Parametros!$B$10 -> 157236.36 | G13: =Parametros!$B$11/Parametros!$B$14 -> 75000 | H13: =MAX(0,E13-F13-G13)*Parametros!$B$13 -> 0 | I13: =E13-F13-H13 -> 909803.64 | J13: =I13/(1+Parametros!$B$12)^B13 -> 853792.91 | K13: =K12+I13 -> -436646.29
A14: 9 | B14: =A14/12 -> 0.75 | C14: =Parametros!$B$5/(1+Parametros!$B$6*B14) -> 590.16393 | D14: =C14*30.4 -> 17940.984 | E14: =D14*Parametros!$B$7*(1-Parametros!$B$8) -> 1026224.3 | F14: =D14*Parametros!$B$9+Parametros!$B$10 -> 151527.87 | G14: =Parametros!$B$11/Parametros!$B$14 -> 75000 | H14: =MAX(0,E14-F14-G14)*Parametros!$B$13 -> 0 | I14: =E14-F14-H14 -> 874696.39 | J14: =I14/(1+Parametros!$B$12)^B14 -> 814353.23 | K14: =K13+I14 -> 438050.11
A15: 10 | B15: =A15/12 -> 0.83333333 | C15: =Parametros!$B$5/(1+Parametros!$B$6*B15) -> 568.42105 | D15: =C15*30.4 -> 17280 | E15: =D15*Parametros!$B$7*(1-Parametros!$B$8) -> 988416 | F15: =D15*Parametros!$B$9+Parametros!$B$10 -> 146240 | G15: =Parametros!$B$11/Parametros!$B$14 -> 75000 | H15: =MAX(0,E15-F15-G15)*Parametros!$B$13 -> 0 | I15: =E15-F15-H15 -> 842176 | J15: =I15/(1+Parametros!$B$12)^B15 -> 777873.46 | K15: =K14+I15 -> 1280226.1
A16: 11 | B16: =A16/12 -> 0.91666667 | C16: =Parametros!$B$5/(1+Parametros!$B$6*B16) -> 548.22335 | D16: =C16*30.4 -> 16665.99 | E16: =D16*Parametros!$B$7*(1-Parametros!$B$8) -> 953294.62 | F16: =D16*Parametros!$B$9+Parametros!$B$10 -> 141327.92 | G16: =Parametros!$B$11/Parametros!$B$14 -> 75000 | H16: =MAX(0,E16-F16-G16)*Parametros!$B$13 -> 0 | I16: =E16-F16-H16 -> 811966.7 | J16: =I16/(1+Parametros!$B$12)^B16 -> 744037.67 | K16: =K15+I16 -> 2092192.8
A17: 12 | B17: =A17/12 -> 1 | C17: =Parametros!$B$5/(1+Parametros!$B$6*B17) -> 529.41176 | D17: =C17*30.4 -> 16094.118 | E17: =D17*Parametros!$B$7*(1-Parametros!$B$8) -> 920583.53 | F17: =D17*Parametros!$B$9+Parametros!$B$10 -> 136752.94 | G17: =Parametros!$B$11/Parametros!$B$14 -> 75000 | H17: =MAX(0,E17-F17-G17)*Parametros!$B$13 -> 0 | I17: =E17-F17-H17 -> 783830.59 | J17: =I17/(1+Parametros!$B$12)^B17 -> 712573.26 | K17: =K16+I17 -> 2876023.4
... A125: 120 | B125: =A125/12 -> 10 | C125: =Parametros!$B$5/(1+Parametros!$B$6*B125) -> 112.5 | D125: =C125*30.4 -> 3420 | E125: =D125*Parametros!$B$7*(1-Parametros!$B$8) -> 195624 | F125: =D125*Parametros!$B$9+Parametros!$B$10 -> 35360 | G125: =Parametros!$B$11/Parametros!$B$14 -> 75000 | H125: =MAX(0,E125-F125-G125)*Parametros!$B$13 -> 0 | I125: =E125-F125-H125 -> 160264 | J125: =I125/(1+Parametros!$B$12)^B125 -> 61788.71 | K125: =K124+I125 -> 37443136

Sheet Indicadores
A1: Indicadores del proyecto
A2: Datos de ejemplo (sintéticos) con fines didácticos. Celdas azules sobre fondo crema = entradas editables; el resto son fórmulas.
A4: Indicador | B4: Valor | C4: Unidad
A5: VPN | B5: =SUM(Flujo!J5:J125)/1000000 -> 25.688146 | C5: MUSD
A6: TIR anual | B6: =(1+IRR(Flujo!I5:I125,0.02))^12-1 -> 2.1268749
A7: Payback (meses con acumulado negativo) | B7: =COUNTIF(Flujo!K5:K125,"<0") -> 9 | C7: meses
A8: Producción acumulada | B8: =SUM(Flujo!D6:D125)/1000 -> 963.47837 | C8: Mbbl
A9: VPN / inversión | B9: =B5*1000000/Parametros!B11 -> 2.8542384
A10: Costo de desarrollo (CAPEX / producción) | B10: =Parametros!B11/(B8*1000) -> 9.3411542 | C10: USD/bbl

Sheet Tornado
A1: Sensibilidad del VPN antes de impuestos (una variable por vez)
A2: Datos de ejemplo (sintéticos) con fines didácticos. Celdas azules sobre fondo crema = entradas editables; el resto son fórmulas.
A3: Variación (±) | B3: 0.2
A5: Variable | B5: VPN con −variación (MUSD) | C5: VPN con +variación (MUSD) | D5: Mínimo | E5: Máximo | F5: Rango
A6: Precio | B6: =(SUMPRODUCT(((Parametros!$B$5/(1+Parametros!$B$6*Flujo!$B$6:$B$125))*30.4*(Parametros!$B$7*(1-$B$3)*(1-Parametros!$B$8)-Parametros!$B$9)-Parametros!$B$10)/(1+Parametros!$B$12)^Flujo!$B$6:$B$125)-Parametros!$B$11)/1000000 -> 17.47911 | C6: =(SUMPRODUCT(((Parametros!$B$5/(1+Parametros!$B$6*Flujo!$B$6:$B$125))*30.4*(Parametros!$B$7*(1+$B$3)*(1-Parametros!$B$8)-Parametros!$B$9)-Parametros!$B$10)/(1+Parametros!$B$12)^Flujo!$B$6:$B$125)-Parametros!$B$11)/1000000 -> 33.897182 | D6: =MIN(B6:C6) -> 17.47911 | E6: =MAX(B6:C6) -> 33.897182 | F6: =E6-D6 -> 16.418072
A7: Producción inicial (qi) | B7: =(SUMPRODUCT(((Parametros!$B$5*(1-$B$3)/(1+Parametros!$B$6*Flujo!$B$6:$B$125))*30.4*(Parametros!$B$7*(1-Parametros!$B$8)-Parametros!$B$9)-Parametros!$B$10)/(1+Parametros!$B$12)^Flujo!$B$6:$B$125)-Parametros!$B$11)/1000000 -> 18.627227 | C7: =(SUMPRODUCT(((Parametros!$B$5*(1+$B$3)/(1+Parametros!$B$6*Flujo!$B$6:$B$125))*30.4*(Parametros!$B$7*(1-Parametros!$B$8)-Parametros!$B$9)-Parametros!$B$10)/(1+Parametros!$B$12)^Flujo!$B$6:$B$125)-Parametros!$B$11)/1000000 -> 32.749065 | D7: =MIN(B7:C7) -> 18.627227 | E7: =MAX(B7:C7) -> 32.749065 | F7: =E7-D7 -> 14.121838
A8: CAPEX | B8: =(SUMPRODUCT(((Parametros!$B$5/(1+Parametros!$B$6*Flujo!$B$6:$B$125))*30.4*(Parametros!$B$7*(1-Parametros!$B$8)-Parametros!$B$9)-Parametros!$B$10)/(1+Parametros!$B$12)^Flujo!$B$6:$B$125)-Parametros!$B$11*(1-$B$3))/1000000 -> 27.488146 | C8: =(SUMPRODUCT(((Parametros!$B$5/(1+Parametros!$B$6*Flujo!$B$6:$B$125))*30.4*(Parametros!$B$7*(1-Parametros!$B$8)-Parametros!$B$9)-Parametros!$B$10)/(1+Parametros!$B$12)^Flujo!$B$6:$B$125)-Parametros!$B$11*(1+$B$3))/1000000 -> 23.888146 | D8: =MIN(B8:C8) -> 23.888146 | E8: =MAX(B8:C8) -> 27.488146 | F8: =E8-D8 -> 3.6
A9: Declinación (Di) | B9: =(SUMPRODUCT(((Parametros!$B$5/(1+Parametros!$B$6*(1-$B$3)*Flujo!$B$6:$B$125))*30.4*(Parametros!$B$7*(1-Parametros!$B$8)-Parametros!$B$9)-Parametros!$B$10)/(1+Parametros!$B$12)^Flujo!$B$6:$B$125)-Parametros!$B$11)/1000000 -> 30.030177 | C9: =(SUMPRODUCT(((Parametros!$B$5/(1+Parametros!$B$6*(1+$B$3)*Flujo!$B$6:$B$125))*30.4*(Parametros!$B$7*(1-Parametros!$B$8)-Parametros!$B$9)-Parametros!$B$10)/(1+Parametros!$B$12)^Flujo!$B$6:$B$125)-Parametros!$B$11)/1000000 -> 22.336478 | D9: =MIN(B9:C9) -> 22.336478 | E9: =MAX(B9:C9) -> 30.030177 | F9: =E9-D9 -> 7.6936991
A10: Tasa de descuento | B10: =(SUMPRODUCT(((Parametros!$B$5/(1+Parametros!$B$6*Flujo!$B$6:$B$125))*30.4*(Parametros!$B$7*(1-Parametros!$B$8)-Parametros!$B$9)-Parametros!$B$10)/(1+Parametros!$B$12*(1-$B$3))^Flujo!$B$6:$B$125)-Parametros!$B$11)/1000000 -> 27.516791 | C10: =(SUMPRODUCT(((Parametros!$B$5/(1+Parametros!$B$6*Flujo!$B$6:$B$125))*30.4*(Parametros!$B$7*(1-Parametros!$B$8)-Parametros!$B$9)-Parametros!$B$10)/(1+Parametros!$B$12*(1+$B$3))^Flujo!$B$6:$B$125)-Parametros!$B$11)/1000000 -> 24.048527 | D10: =MIN(B10:C10) -> 24.048527 | E10: =MAX(B10:C10) -> 27.516791 | F10: =E10-D10 -> 3.4682644
A11: Costos operativos | B11: =(SUMPRODUCT(((Parametros!$B$5/(1+Parametros!$B$6*Flujo!$B$6:$B$125))*30.4*(Parametros!$B$7*(1-Parametros!$B$8)-Parametros!$B$9*(1-$B$3))-Parametros!$B$10*(1-$B$3))/(1+Parametros!$B$12)^Flujo!$B$6:$B$125)-Parametros!$B$11)/1000000 -> 26.959553 | C11: =(SUMPRODUCT(((Parametros!$B$5/(1+Parametros!$B$6*Flujo!$B$6:$B$125))*30.4*(Parametros!$B$7*(1-Parametros!$B$8)-Parametros!$B$9*(1+$B$3))-Parametros!$B$10*(1+$B$3))/(1+Parametros!$B$12)^Flujo!$B$6:$B$125)-Parametros!$B$11)/1000000 -> 24.416739 | D11: =MIN(B11:C11) -> 24.416739 | E11: =MAX(B11:C11) -> 26.959553 | F11: =E11-D11 -> 2.5428136
A13: VPN base (antes de impuestos) | B13: =(SUMPRODUCT(((Parametros!$B$5/(1+Parametros!$B$6*Flujo!$B$6:$B$125))*30.4*(Parametros!$B$7*(1-Parametros!$B$8)-Parametros!$B$9)-Parametros!$B$10)/(1+Parametros!$B$12)^Flujo!$B$6:$B$125)-Parametros!$B$11)/1000000 -> 25.688146
A14: Variable con mayor rango | B14: =INDEX(A6:A11,MATCH(MAX(F6:F11),F6:F11,0)) -> Precio
A16: Para ordenar el gráfico tipo tornado, ordená la tabla por la columna Rango (de mayor a menor).

Sheet Decision
A1: Decisión de perforar un pozo exploratorio y efecto del portafolio
A2: Datos de ejemplo (sintéticos) con fines didácticos. Celdas azules sobre fondo crema = entradas editables; el resto son fórmulas.
A4: Probabilidad de éxito P | B4: 0.25
A5: VPN si hay éxito (MUSD) | B5: 120
A6: Costo si es seco (MUSD) | B6: 20
A7: Número de pozos independientes | B7: 10
A9: VME de un pozo (MUSD) | B9: =B4*B5-(1-B4)*B6 -> 15
A10: Probabilidad de equilibrio P* = C/(V+C) | B10: =B6/(B5+B6) -> 0.14285714
A11: VME del portafolio (MUSD) | B11: =B9*B7 -> 150
A12: Probabilidad de pérdida del portafolio | B12: =SUM(G16:G46) -> 0.24402523
A15: Éxitos k | B15: Fracaso | C15: Resultado (MUSD) | D15: Probabilidad | E15: ¿Pérdida? | G15: Prob. con pérdida
A16: 0 | B16: =IF(A16<=$B$7,$B$7-A16,"") -> 10 | C16: =IF(A16<=$B$7,A16*$B$5-($B$7-A16)*$B$6,"") -> -200 | D16: =IF(A16<=$B$7,BINOMDIST(A16,$B$7,$B$4,FALSE()),0) -> 0.056313515 | E16: =IF(A16<=$B$7,IF(C16<0,1,0),0) -> 1 | G16: =D16*E16 -> 0.056313515
A17: 1 | B17: =IF(A17<=$B$7,$B$7-A17,"") -> 9 | C17: =IF(A17<=$B$7,A17*$B$5-($B$7-A17)*$B$6,"") -> -60 | D17: =IF(A17<=$B$7,BINOMDIST(A17,$B$7,$B$4,FALSE()),0) -> 0.18771172 | E17: =IF(A17<=$B$7,IF(C17<0,1,0),0) -> 1 | G17: =D17*E17 -> 0.18771172
A18: 2 | B18: =IF(A18<=$B$7,$B$7-A18,"") -> 8 | C18: =IF(A18<=$B$7,A18*$B$5-($B$7-A18)*$B$6,"") -> 80 | D18: =IF(A18<=$B$7,BINOMDIST(A18,$B$7,$B$4,FALSE()),0) -> 0.28156757 | E18: =IF(A18<=$B$7,IF(C18<0,1,0),0) -> 0 | G18: =D18*E18 -> 0
A19: 3 | B19: =IF(A19<=$B$7,$B$7-A19,"") -> 7 | C19: =IF(A19<=$B$7,A19*$B$5-($B$7-A19)*$B$6,"") -> 220 | D19: =IF(A19<=$B$7,BINOMDIST(A19,$B$7,$B$4,FALSE()),0) -> 0.25028229 | E19: =IF(A19<=$B$7,IF(C19<0,1,0),0) -> 0 | G19: =D19*E19 -> 0
A20: 4 | B20: =IF(A20<=$B$7,$B$7-A20,"") -> 6 | C20: =IF(A20<=$B$7,A20*$B$5-($B$7-A20)*$B$6,"") -> 360 | D20: =IF(A20<=$B$7,BINOMDIST(A20,$B$7,$B$4,FALSE()),0) -> 0.145998 | E20: =IF(A20<=$B$7,IF(C20<0,1,0),0) -> 0 | G20: =D20*E20 -> 0
A21: 5 | B21: =IF(A21<=$B$7,$B$7-A21,"") -> 5 | C21: =IF(A21<=$B$7,A21*$B$5-($B$7-A21)*$B$6,"") -> 500 | D21: =IF(A21<=$B$7,BINOMDIST(A21,$B$7,$B$4,FALSE()),0) -> 0.0583992 | E21: =IF(A21<=$B$7,IF(C21<0,1,0),0) -> 0 | G21: =D21*E21 -> 0
A22: 6 | B22: =IF(A22<=$B$7,$B$7-A22,"") -> 4 | C22: =IF(A22<=$B$7,A22*$B$5-($B$7-A22)*$B$6,"") -> 640 | D22: =IF(A22<=$B$7,BINOMDIST(A22,$B$7,$B$4,FALSE()),0) -> 0.016222 | E22: =IF(A22<=$B$7,IF(C22<0,1,0),0) -> 0 | G22: =D22*E22 -> 0
A23: 7 | B23: =IF(A23<=$B$7,$B$7-A23,"") -> 3 | C23: =IF(A23<=$B$7,A23*$B$5-($B$7-A23)*$B$6,"") -> 780 | D23: =IF(A23<=$B$7,BINOMDIST(A23,$B$7,$B$4,FALSE()),0) -> 0.0030899048 | E23: =IF(A23<=$B$7,IF(C23<0,1,0),0) -> 0 | G23: =D23*E23 -> 0
A24: 8 | B24: =IF(A24<=$B$7,$B$7-A24,"") -> 2 | C24: =IF(A24<=$B$7,A24*$B$5-($B$7-A24)*$B$6,"") -> 920 | D24: =IF(A24<=$B$7,BINOMDIST(A24,$B$7,$B$4,FALSE()),0) -> 0.0003862381 | E24: =IF(A24<=$B$7,IF(C24<0,1,0),0) -> 0 | G24: =D24*E24 -> 0
A25: 9 | B25: =IF(A25<=$B$7,$B$7-A25,"") -> 1 | C25: =IF(A25<=$B$7,A25*$B$5-($B$7-A25)*$B$6,"") -> 1060 | D25: =IF(A25<=$B$7,BINOMDIST(A25,$B$7,$B$4,FALSE()),0) -> 2.8610229e-05 | E25: =IF(A25<=$B$7,IF(C25<0,1,0),0) -> 0 | G25: =D25*E25 -> 0
A26: 10 | B26: =IF(A26<=$B$7,$B$7-A26,"") -> 0 | C26: =IF(A26<=$B$7,A26*$B$5-($B$7-A26)*$B$6,"") -> 1200 | D26: =IF(A26<=$B$7,BINOMDIST(A26,$B$7,$B$4,FALSE()),0) -> 9.5367432e-07 | E26: =IF(A26<=$B$7,IF(C26<0,1,0),0) -> 0 | G26: =D26*E26 -> 0
A27: 11 | B27: =IF(A27<=$B$7,$B$7-A27,"") | C27: =IF(A27<=$B$7,A27*$B$5-($B$7-A27)*$B$6,"") | D27: =IF(A27<=$B$7,BINOMDIST(A27,$B$7,$B$4,FALSE()),0) -> 0 | E27: =IF(A27<=$B$7,IF(C27<0,1,0),0) -> 0 | G27: =D27*E27 -> 0
... A46: 30 | B46: =IF(A46<=$B$7,$B$7-A46,"") | C46: =IF(A46<=$B$7,A46*$B$5-($B$7-A46)*$B$6,"") | D46: =IF(A46<=$B$7,BINOMDIST(A46,$B$7,$B$4,FALSE()),0) -> 0 | E46: =IF(A46<=$B$7,IF(C46<0,1,0),0) -> 0 | G46: =D46*E46 -> 0
A48: La distribución binomial supone pozos independientes con la misma probabilidad. En la realidad hay correlaciones geológicas. Hasta 30 pozos.
