Workbook

Sheet Parametros
A1: Declinación de Arps, EUR y límite económico
A2: Datos de ejemplo (sintéticos) con fines didácticos. Celdas azules sobre fondo crema = entradas editables; el resto son fórmulas.
A4: Escenario | B4: qi (bbl/d) | C4: Di nominal (1/año) | D4: b | E4: Descripción
A5: Bajo (1P) | B5: 380 | C5: 0.95 | D5: 0.4 | E5: Estimación baja
A6: Mejor (2P) | B6: 450 | C6: 0.8 | D6: 0.8 | E6: Estimación mejor
A7: Alto (3P) | B7: 520 | C7: 0.65 | D7: 1.2 | E7: Estimación alta
A10: Economía | B10: Valor | C10: Unidad
A11: Precio del crudo | B11: 65 | C11: USD/bbl
A12: Regalías | B12: 0.12 | C12: fracción
A13: Opex variable | B13: 9 | C13: USD/bbl
A14: Opex fijo | B14: 9000 | C14: USD/mes
A15: CAPEX (pozo) | B15: 6500000 | C15: USD
A16: Tasa de descuento | B16: 0.1 | C16: anual
A18: Margen neto por barril | B18: =B11*(1-B12)-B13 -> 48.2 | C18: USD/bbl
A19: Caudal límite económico (aprox.) | B19: =B14/(B18*30.4) -> 6.1421708 | C19: bbl/d
A21: q(t) = qi / (1 + b·Di·t)^(1/b), t en años. Mes económico si margen·volumen − opex fijo > 0. Para b=0 usar exponencial (no cubierto aquí; usar b>0).

Sheet Pronostico
A1: Pronóstico mensual (240 meses)
A2: Datos de ejemplo (sintéticos) con fines didácticos. Celdas azules sobre fondo crema = entradas editables; el resto son fórmulas.
A4: Mes | B4: q Bajo (bbl/d) | C4: Vol Bajo (bbl) | D4: Econ. Bajo | E4: Flujo Bajo (USD) | F4: q Mejor (bbl/d) | G4: Vol Mejor (bbl) | H4: Econ. Mejor | I4: Flujo Mejor (USD) | J4: q Alto (bbl/d) | K4: Vol Alto (bbl) | L4: Econ. Alto | M4: Flujo Alto (USD)
A5: 1 | B5: =Parametros!$B$5/(1+Parametros!$D$5*Parametros!$C$5*A5/12)^(1/Parametros!$D$5) -> 351.50791 | C5: =B5*30.4 -> 10685.84 | D5: =IF(Parametros!$B$18*C5-Parametros!$B$14>0,1,0) -> 1 | E5: =(C5*Parametros!$B$18-Parametros!$B$14)*D5/(1+Parametros!$B$16)^(A5/12) -> 502054.06 | F5: =Parametros!$B$6/(1+Parametros!$D$6*Parametros!$C$6*A5/12)^(1/Parametros!$D$6) -> 421.70158 | G5: =F5*30.4 -> 12819.728 | H5: =IF(Parametros!$B$18*G5-Parametros!$B$14>0,1,0) -> 1 | I5: =(G5*Parametros!$B$18-Parametros!$B$14)*H5/(1+Parametros!$B$16)^(A5/12) -> 604093.76 | J5: =Parametros!$B$7/(1+Parametros!$D$7*Parametros!$C$7*A5/12)^(1/Parametros!$D$7) -> 493.41461 | K5: =J5*30.4 -> 14999.804 | L5: =IF(Parametros!$B$18*K5-Parametros!$B$14>0,1,0) -> 1 | M5: =(K5*Parametros!$B$18-Parametros!$B$14)*L5/(1+Parametros!$B$16)^(A5/12) -> 708342.14
A6: 2 | B6: =Parametros!$B$5/(1+Parametros!$D$5*Parametros!$C$5*A6/12)^(1/Parametros!$D$5) -> 325.91926 | C6: =B6*30.4 -> 9907.9455 | D6: =IF(Parametros!$B$18*C6-Parametros!$B$14>0,1,0) -> 1 | E6: =(C6*Parametros!$B$18-Parametros!$B$14)*D6/(1+Parametros!$B$16)^(A6/12) -> 461178.64 | F6: =Parametros!$B$6/(1+Parametros!$D$6*Parametros!$C$6*A6/12)^(1/Parametros!$D$6) -> 396.45279 | G6: =F6*30.4 -> 12052.165 | H6: =IF(Parametros!$B$18*G6-Parametros!$B$14>0,1,0) -> 1 | I6: =(G6*Parametros!$B$18-Parametros!$B$14)*H6/(1+Parametros!$B$16)^(A6/12) -> 562901.24 | J6: =Parametros!$B$7/(1+Parametros!$D$7*Parametros!$C$7*A6/12)^(1/Parametros!$D$7) -> 469.64673 | K6: =J6*30.4 -> 14277.261 | L6: =IF(Parametros!$B$18*K6-Parametros!$B$14>0,1,0) -> 1 | M6: =(K6*Parametros!$B$18-Parametros!$B$14)*L6/(1+Parametros!$B$16)^(A6/12) -> 668460.66
A7: 3 | B7: =Parametros!$B$5/(1+Parametros!$D$5*Parametros!$C$5*A7/12)^(1/Parametros!$D$5) -> 302.86445 | C7: =B7*30.4 -> 9207.0793 | D7: =IF(Parametros!$B$18*C7-Parametros!$B$14>0,1,0) -> 1 | E7: =(C7*Parametros!$B$18-Parametros!$B$14)*D7/(1+Parametros!$B$16)^(A7/12) -> 424543.9 | F7: =Parametros!$B$6/(1+Parametros!$D$6*Parametros!$C$6*A7/12)^(1/Parametros!$D$6) -> 373.80063 | G7: =F7*30.4 -> 11363.539 | H7: =IF(Parametros!$B$18*G7-Parametros!$B$14>0,1,0) -> 1 | I7: =(G7*Parametros!$B$18-Parametros!$B$14)*H7/(1+Parametros!$B$16)^(A7/12) -> 526037.87 | J7: =Parametros!$B$7/(1+Parametros!$D$7*Parametros!$C$7*A7/12)^(1/Parametros!$D$7) -> 448.26011 | K7: =J7*30.4 -> 13627.107 | L7: =IF(Parametros!$B$18*K7-Parametros!$B$14>0,1,0) -> 1 | M7: =(K7*Parametros!$B$18-Parametros!$B$14)*L7/(1+Parametros!$B$16)^(A7/12) -> 632572.9
A8: 4 | B8: =Parametros!$B$5/(1+Parametros!$D$5*Parametros!$C$5*A8/12)^(1/Parametros!$D$5) -> 282.02979 | C8: =B8*30.4 -> 8573.7056 | D8: =IF(Parametros!$B$18*C8-Parametros!$B$14>0,1,0) -> 1 | E8: =(C8*Parametros!$B$18-Parametros!$B$14)*D8/(1+Parametros!$B$16)^(A8/12) -> 391611.35 | F8: =Parametros!$B$6/(1+Parametros!$D$6*Parametros!$C$6*A8/12)^(1/Parametros!$D$6) -> 353.37625 | G8: =F8*30.4 -> 10742.638 | H8: =IF(Parametros!$B$18*G8-Parametros!$B$14>0,1,0) -> 1 | I8: =(G8*Parametros!$B$18-Parametros!$B$14)*H8/(1+Parametros!$B$16)^(A8/12) -> 492884.77 | J8: =Parametros!$B$7/(1+Parametros!$D$7*Parametros!$C$7*A8/12)^(1/Parametros!$D$7) -> 428.90511 | K8: =J8*30.4 -> 13038.715 | L8: =IF(Parametros!$B$18*K8-Parametros!$B$14>0,1,0) -> 1 | M8: =(K8*Parametros!$B$18-Parametros!$B$14)*L8/(1+Parametros!$B$16)^(A8/12) -> 600094.95
A9: 5 | B9: =Parametros!$B$5/(1+Parametros!$D$5*Parametros!$C$5*A9/12)^(1/Parametros!$D$5) -> 263.14778 | C9: =B9*30.4 -> 7999.6925 | D9: =IF(Parametros!$B$18*C9-Parametros!$B$14>0,1,0) -> 1 | E9: =(C9*Parametros!$B$18-Parametros!$B$14)*D9/(1+Parametros!$B$16)^(A9/12) -> 361923.07 | F9: =Parametros!$B$6/(1+Parametros!$D$6*Parametros!$C$6*A9/12)^(1/Parametros!$D$6) -> 334.87643 | G9: =F9*30.4 -> 10180.244 | H9: =IF(Parametros!$B$18*G9-Parametros!$B$14>0,1,0) -> 1 | I9: =(G9*Parametros!$B$18-Parametros!$B$14)*H9/(1+Parametros!$B$16)^(A9/12) -> 462933.53 | J9: =Parametros!$B$7/(1+Parametros!$D$7*Parametros!$C$7*A9/12)^(1/Parametros!$D$7) -> 411.29817 | K9: =J9*30.4 -> 12503.464 | L9: =IF(Parametros!$B$18*K9-Parametros!$B$14>0,1,0) -> 1 | M9: =(K9*Parametros!$B$18-Parametros!$B$14)*L9/(1+Parametros!$B$16)^(A9/12) -> 570552.94
A10: 6 | B10: =Parametros!$B$5/(1+Parametros!$D$5*Parametros!$C$5*A10/12)^(1/Parametros!$D$5) -> 245.98929 | C10: =B10*30.4 -> 7478.0743 | D10: =IF(Parametros!$B$18*C10-Parametros!$B$14>0,1,0) -> 1 | E10: =(C10*Parametros!$B$18-Parametros!$B$14)*D10/(1+Parametros!$B$16)^(A10/12) -> 335087.93 | F10: =Parametros!$B$6/(1+Parametros!$D$6*Parametros!$C$6*A10/12)^(1/Parametros!$D$6) -> 318.04978 | G10: =F10*30.4 -> 9668.7133 | H10: =IF(Parametros!$B$18*G10-Parametros!$B$14>0,1,0) -> 1 | I10: =(G10*Parametros!$B$18-Parametros!$B$14)*H10/(1+Parametros!$B$16)^(A10/12) -> 435762.9 | J10: =Parametros!$B$7/(1+Parametros!$D$7*Parametros!$C$7*A10/12)^(1/Parametros!$D$7) -> 395.20674 | K10: =J10*30.4 -> 12014.285 | L10: =IF(Parametros!$B$18*K10-Parametros!$B$14>0,1,0) -> 1 | M10: =(K10*Parametros!$B$18-Parametros!$B$14)*L10/(1+Parametros!$B$16)^(A10/12) -> 543558.09
A11: 7 | B11: =Parametros!$B$5/(1+Parametros!$D$5*Parametros!$C$5*A11/12)^(1/Parametros!$D$5) -> 230.3572 | C11: =B11*30.4 -> 7002.8588 | D11: =IF(Parametros!$B$18*C11-Parametros!$B$14>0,1,0) -> 1 | E11: =(C11*Parametros!$B$18-Parametros!$B$14)*D11/(1+Parametros!$B$16)^(A11/12) -> 310770.37 | F11: =Parametros!$B$6/(1+Parametros!$D$6*Parametros!$C$6*A11/12)^(1/Parametros!$D$6) -> 302.68616 | G11: =F11*30.4 -> 9201.6592 | H11: =IF(Parametros!$B$18*G11-Parametros!$B$14>0,1,0) -> 1 | I11: =(G11*Parametros!$B$18-Parametros!$B$14)*H11/(1+Parametros!$B$16)^(A11/12) -> 411021 | J11: =Parametros!$B$7/(1+Parametros!$D$7*Parametros!$C$7*A11/12)^(1/Parametros!$D$7) -> 380.43826 | K11: =J11*30.4 -> 11565.323 | L11: =IF(Parametros!$B$18*K11-Parametros!$B$14>0,1,0) -> 1 | M11: =(K11*Parametros!$B$18-Parametros!$B$14)*L11/(1+Parametros!$B$16)^(A11/12) -> 518788.3
A12: 8 | B12: =Parametros!$B$5/(1+Parametros!$D$5*Parametros!$C$5*A12/12)^(1/Parametros!$D$5) -> 216.08127 | C12: =B12*30.4 -> 6568.8706 | D12: =IF(Parametros!$B$18*C12-Parametros!$B$14>0,1,0) -> 1 | E12: =(C12*Parametros!$B$18-Parametros!$B$14)*D12/(1+Parametros!$B$16)^(A12/12) -> 288681.41 | F12: =Parametros!$B$6/(1+Parametros!$D$6*Parametros!$C$6*A12/12)^(1/Parametros!$D$6) -> 288.60867 | G12: =F12*30.4 -> 8773.7035 | H12: =IF(Parametros!$B$18*G12-Parametros!$B$14>0,1,0) -> 1 | I12: =(G12*Parametros!$B$18-Parametros!$B$14)*H12/(1+Parametros!$B$16)^(A12/12) -> 388411.82 | J12: =Parametros!$B$7/(1+Parametros!$D$7*Parametros!$C$7*A12/12)^(1/Parametros!$D$7) -> 366.83184 | K12: =J12*30.4 -> 11151.688 | L12: =IF(Parametros!$B$18*K12-Parametros!$B$14>0,1,0) -> 1 | M12: =(K12*Parametros!$B$18-Parametros!$B$14)*L12/(1+Parametros!$B$16)^(A12/12) -> 495974.33
A13: 9 | B13: =Parametros!$B$5/(1+Parametros!$D$5*Parametros!$C$5*A13/12)^(1/Parametros!$D$5) -> 203.0139 | C13: =B13*30.4 -> 6171.6226 | D13: =IF(Parametros!$B$18*C13-Parametros!$B$14>0,1,0) -> 1 | E13: =(C13*Parametros!$B$18-Parametros!$B$14)*D13/(1+Parametros!$B$16)^(A13/12) -> 268571.22 | F13: =Parametros!$B$6/(1+Parametros!$D$6*Parametros!$C$6*A13/12)^(1/Parametros!$D$6) -> 275.66737 | G13: =F13*30.4 -> 8380.2882 | H13: =IF(Parametros!$B$18*G13-Parametros!$B$14>0,1,0) -> 1 | I13: =(G13*Parametros!$B$18-Parametros!$B$14)*H13/(1+Parametros!$B$16)^(A13/12) -> 367684.64 | J13: =Parametros!$B$7/(1+Parametros!$D$7*Parametros!$C$7*A13/12)^(1/Parametros!$D$7) -> 354.25198 | K13: =J13*30.4 -> 10769.26 | L13: =IF(Parametros!$B$18*K13-Parametros!$B$14>0,1,0) -> 1 | M13: =(K13*Parametros!$B$18-Parametros!$B$14)*L13/(1+Parametros!$B$16)^(A13/12) -> 474889.29
A14: 10 | B14: =Parametros!$B$5/(1+Parametros!$D$5*Parametros!$C$5*A14/12)^(1/Parametros!$D$5) -> 191.02667 | C14: =B14*30.4 -> 5807.2106 | D14: =IF(Parametros!$B$18*C14-Parametros!$B$14>0,1,0) -> 1 | E14: =(C14*Parametros!$B$18-Parametros!$B$14)*D14/(1+Parametros!$B$16)^(A14/12) -> 250222.99 | F14: =Parametros!$B$6/(1+Parametros!$D$6*Parametros!$C$6*A14/12)^(1/Parametros!$D$6) -> 263.73441 | G14: =F14*30.4 -> 8017.526 | H14: =IF(Parametros!$B$18*G14-Parametros!$B$14>0,1,0) -> 1 | I14: =(G14*Parametros!$B$18-Parametros!$B$14)*H14/(1+Parametros!$B$16)^(A14/12) -> 348625.77 | J14: =Parametros!$B$7/(1+Parametros!$D$7*Parametros!$C$7*A14/12)^(1/Parametros!$D$7) -> 342.58372 | K14: =J14*30.4 -> 10414.545 | L14: =IF(Parametros!$B$18*K14-Parametros!$B$14>0,1,0) -> 1 | M14: =(K14*Parametros!$B$18-Parametros!$B$14)*L14/(1+Parametros!$B$16)^(A14/12) -> 455340.57
A15: 11 | B15: =Parametros!$B$5/(1+Parametros!$D$5*Parametros!$C$5*A15/12)^(1/Parametros!$D$5) -> 180.00742 | C15: =B15*30.4 -> 5472.2257 | D15: =IF(Parametros!$B$18*C15-Parametros!$B$14>0,1,0) -> 1 | E15: =(C15*Parametros!$B$18-Parametros!$B$14)*D15/(1+Parametros!$B$16)^(A15/12) -> 233447.98 | F15: =Parametros!$B$6/(1+Parametros!$D$6*Parametros!$C$6*A15/12)^(1/Parametros!$D$6) -> 252.70009 | G15: =F15*30.4 -> 7682.0826 | H15: =IF(Parametros!$B$18*G15-Parametros!$B$14>0,1,0) -> 1 | I15: =(G15*Parametros!$B$18-Parametros!$B$14)*H15/(1+Parametros!$B$16)^(A15/12) -> 331052.05 | J15: =Parametros!$B$7/(1+Parametros!$D$7*Parametros!$C$7*A15/12)^(1/Parametros!$D$7) -> 331.72885 | K15: =J15*30.4 -> 10084.557 | L15: =IF(Parametros!$B$18*K15-Parametros!$B$14>0,1,0) -> 1 | M15: =(K15*Parametros!$B$18-Parametros!$B$14)*L15/(1+Parametros!$B$16)^(A15/12) -> 437163.56
A16: 12 | B16: =Parametros!$B$5/(1+Parametros!$D$5*Parametros!$C$5*A16/12)^(1/Parametros!$D$5) -> 169.85795 | C16: =B16*30.4 -> 5163.6817 | D16: =IF(Parametros!$B$18*C16-Parametros!$B$14>0,1,0) -> 1 | E16: =(C16*Parametros!$B$18-Parametros!$B$14)*D16/(1+Parametros!$B$16)^(A16/12) -> 218081.33 | F16: =Parametros!$B$6/(1+Parametros!$D$6*Parametros!$C$6*A16/12)^(1/Parametros!$D$6) -> 242.46983 | G16: =F16*30.4 -> 7371.0828 | H16: =IF(Parametros!$B$18*G16-Parametros!$B$14>0,1,0) -> 1 | I16: =(G16*Parametros!$B$18-Parametros!$B$14)*H16/(1+Parametros!$B$16)^(A16/12) -> 314805.63 | J16: =Parametros!$B$7/(1+Parametros!$D$7*Parametros!$C$7*A16/12)^(1/Parametros!$D$7) -> 321.60294 | K16: =J16*30.4 -> 9776.7293 | L16: =IF(Parametros!$B$18*K16-Parametros!$B$14>0,1,0) -> 1 | M16: =(K16*Parametros!$B$18-Parametros!$B$14)*L16/(1+Parametros!$B$16)^(A16/12) -> 420216.69
... A244: 240 | B244: =Parametros!$B$5/(1+Parametros!$D$5*Parametros!$C$5*A244/12)^(1/Parametros!$D$5) -> 1.7520136 | C244: =B244*30.4 -> 53.261213 | D244: =IF(Parametros!$B$18*C244-Parametros!$B$14>0,1,0) -> 0 | E244: =(C244*Parametros!$B$18-Parametros!$B$14)*D244/(1+Parametros!$B$16)^(A244/12) -> 0 | F244: =Parametros!$B$6/(1+Parametros!$D$6*Parametros!$C$6*A244/12)^(1/Parametros!$D$6) -> 16.91857 | G244: =F244*30.4 -> 514.32453 | H244: =IF(Parametros!$B$18*G244-Parametros!$B$14>0,1,0) -> 1 | I244: =(G244*Parametros!$B$18-Parametros!$B$14)*H244/(1+Parametros!$B$16)^(A244/12) -> 2347.1487 | J244: =Parametros!$B$7/(1+Parametros!$D$7*Parametros!$C$7*A244/12)^(1/Parametros!$D$7) -> 50.031855 | K244: =J244*30.4 -> 1520.9684 | L244: =IF(Parametros!$B$18*K244-Parametros!$B$14>0,1,0) -> 1 | M244: =(K244*Parametros!$B$18-Parametros!$B$14)*L244/(1+Parametros!$B$16)^(A244/12) -> 9559.3722

Sheet Resultados
A1: EUR, VPN y clasificación (ejemplo)
A2: Datos de ejemplo (sintéticos) con fines didácticos. Celdas azules sobre fondo crema = entradas editables; el resto son fórmulas.
A4: Escenario | B4: EUR económico (Mbbl) | C4: VPN10 (MUSD) | D4: ¿Económico? | E4: Vida económica (meses) | F4: Cum. 240 m sin límite (Mbbl)
A5: Bajo (1P) | B5: =SUMPRODUCT(Pronostico!C5:C244,Pronostico!D5:D244)/1000 -> 216.96597 | C5: =(SUM(Pronostico!E5:E244)-Parametros!$B$15)/1000000 -> 1.3872519 | D5: =IF(C5>0,"Sí","No") -> Sí | E5: =SUM(Pronostico!D5:D244) -> 132 | F5: =SUM(Pronostico!C5:C244)/1000 -> 227.8837
A6: Mejor (2P) | B6: =SUMPRODUCT(Pronostico!G5:G244,Pronostico!H5:H244)/1000 -> 487.16704 | C6: =(SUM(Pronostico!I5:I244)-Parametros!$B$15)/1000000 -> 8.3650375 | D6: =IF(C6>0,"Sí","No") -> Sí | E6: =SUM(Pronostico!H5:H244) -> 240 | F6: =SUM(Pronostico!G5:G244)/1000 -> 487.16704
A7: Alto (3P) | B7: =SUMPRODUCT(Pronostico!K5:K244,Pronostico!L5:L244)/1000 -> 864.31896 | C7: =(SUM(Pronostico!M5:M244)-Parametros!$B$15)/1000000 -> 17.656873 | D7: =IF(C7>0,"Sí","No") -> Sí | E7: =SUM(Pronostico!L5:L244) -> 240 | F7: =SUM(Pronostico!K5:K244)/1000 -> 864.31896
A9: Lectura PRMS: 1P/2P/3P se asocian a P90/P50/P10 cuando hay un conjunto probabilístico; acá son tres casos determinísticos. Reservas = económicas bajo el precio supuesto.
