Workbook

Sheet Parametros
A1: Pozo no convencional: declinación hiperbólica modificada y economía simple
A2: Datos de ejemplo (sintéticos) con fines didácticos. Celdas azules sobre fondo crema = entradas editables; el resto son fórmulas.
A4: Parámetro | B4: Valor | C4: Unidad
A5: Caudal inicial qi | B5: 900 | C5: bbl/d
A6: Declinación inicial Di | B6: 0.75 | C6: 1/año
A7: Exponente b | B7: 1.5
A8: Declinación terminal Dmin | B8: 0.06 | C8: 1/año
A9: Precio del crudo | B9: 60 | C9: USD/bbl
A10: Regalías | B10: 0.12 | C10: fracción
A11: Opex variable | B11: 8 | C11: USD/bbl
A12: Opex fijo | B12: 9000 | C12: USD/mes
A13: CAPEX del pozo | B13: 13000000 | C13: USD
A14: Tasa de descuento | B14: 0.1 | C14: anual
A15: Horizonte | B15: 30 | C15: años
A17: Tiempo de cambio a declinación terminal ts | B17: =MAX(0,(B6/B8-1)/(B7*B6)) -> 10.222222 | C17: años
A19: Pozo de ejemplo con datos sintéticos. La hipótesis de b y de Dmin es la que más se discute en una auditoría de reservas.

Sheet Pronostico
A1: Pronóstico mensual (360 meses)
A2: Datos de ejemplo (sintéticos) con fines didácticos. Celdas azules sobre fondo crema = entradas editables; el resto son fórmulas.
A4: Mes | B4: Tiempo (años) | C4: q hiperbólica pura (bbl/d) | D4: q modificada (bbl/d) | E4: Volumen modificado (bbl) | F4: Volumen hiperbólico (bbl) | G4: Flujo de caja (USD)
A5: 1 | B5: =(A5-1)/12 -> 0 | C5: =Parametros!$B$5/(1+Parametros!$B$7*Parametros!$B$6*B5)^(1/Parametros!$B$7) -> 900 | D5: =IF(B5<=Parametros!$B$17,C5,Parametros!$B$5/(1+Parametros!$B$7*Parametros!$B$6*Parametros!$B$17)^(1/Parametros!$B$7)*EXP(-Parametros!$B$8*(B5-Parametros!$B$17))) -> 900 | E5: =D5*30.4*IF(B5<Parametros!$B$15,1,0) -> 27360 | F5: =C5*30.4*IF(B5<Parametros!$B$15,1,0) -> 27360 | G5: =(E5*(Parametros!$B$9*(1-Parametros!$B$10)-Parametros!$B$11)-Parametros!$B$12*IF(B5<Parametros!$B$15,1,0))/(1+Parametros!$B$14)^B5 -> 1216728
A6: 2 | B6: =(A6-1)/12 -> 0.083333333 | C6: =Parametros!$B$5/(1+Parametros!$B$7*Parametros!$B$6*B6)^(1/Parametros!$B$7) -> 847.80726 | D6: =IF(B6<=Parametros!$B$17,C6,Parametros!$B$5/(1+Parametros!$B$7*Parametros!$B$6*Parametros!$B$17)^(1/Parametros!$B$7)*EXP(-Parametros!$B$8*(B6-Parametros!$B$17))) -> 847.80726 | E6: =D6*30.4*IF(B6<Parametros!$B$15,1,0) -> 25773.341 | F6: =C6*30.4*IF(B6<Parametros!$B$15,1,0) -> 25773.341 | G6: =(E6*(Parametros!$B$9*(1-Parametros!$B$10)-Parametros!$B$11)-Parametros!$B$12*IF(B6<Parametros!$B$15,1,0))/(1+Parametros!$B$14)^B6 -> 1136582.4
A7: 3 | B7: =(A7-1)/12 -> 0.16666667 | C7: =Parametros!$B$5/(1+Parametros!$B$7*Parametros!$B$6*B7)^(1/Parametros!$B$7) -> 802.5771 | D7: =IF(B7<=Parametros!$B$17,C7,Parametros!$B$5/(1+Parametros!$B$7*Parametros!$B$6*Parametros!$B$17)^(1/Parametros!$B$7)*EXP(-Parametros!$B$8*(B7-Parametros!$B$17))) -> 802.5771 | E7: =D7*30.4*IF(B7<Parametros!$B$15,1,0) -> 24398.344 | F7: =C7*30.4*IF(B7<Parametros!$B$15,1,0) -> 24398.344 | G7: =(E7*(Parametros!$B$9*(1-Parametros!$B$10)-Parametros!$B$11)-Parametros!$B$12*IF(B7<Parametros!$B$15,1,0))/(1+Parametros!$B$14)^B7 -> 1066961.8
A8: 4 | B8: =(A8-1)/12 -> 0.25 | C8: =Parametros!$B$5/(1+Parametros!$B$7*Parametros!$B$6*B8)^(1/Parametros!$B$7) -> 762.93333 | D8: =IF(B8<=Parametros!$B$17,C8,Parametros!$B$5/(1+Parametros!$B$7*Parametros!$B$6*Parametros!$B$17)^(1/Parametros!$B$7)*EXP(-Parametros!$B$8*(B8-Parametros!$B$17))) -> 762.93333 | E8: =D8*30.4*IF(B8<Parametros!$B$15,1,0) -> 23193.173 | F8: =C8*30.4*IF(B8<Parametros!$B$15,1,0) -> 23193.173 | G8: =(E8*(Parametros!$B$9*(1-Parametros!$B$10)-Parametros!$B$11)-Parametros!$B$12*IF(B8<Parametros!$B$15,1,0))/(1+Parametros!$B$14)^B8 -> 1005800.6
A9: 5 | B9: =(A9-1)/12 -> 0.33333333 | C9: =Parametros!$B$5/(1+Parametros!$B$7*Parametros!$B$6*B9)^(1/Parametros!$B$7) -> 727.84803 | D9: =IF(B9<=Parametros!$B$17,C9,Parametros!$B$5/(1+Parametros!$B$7*Parametros!$B$6*Parametros!$B$17)^(1/Parametros!$B$7)*EXP(-Parametros!$B$8*(B9-Parametros!$B$17))) -> 727.84803 | E9: =D9*30.4*IF(B9<Parametros!$B$15,1,0) -> 22126.58 | F9: =C9*30.4*IF(B9<Parametros!$B$15,1,0) -> 22126.58 | G9: =(E9*(Parametros!$B$9*(1-Parametros!$B$10)-Parametros!$B$11)-Parametros!$B$12*IF(B9<Parametros!$B$15,1,0))/(1+Parametros!$B$14)^B9 -> 951554.5
A10: 6 | B10: =(A10-1)/12 -> 0.41666667 | C10: =Parametros!$B$5/(1+Parametros!$B$7*Parametros!$B$6*B10)^(1/Parametros!$B$7) -> 696.53657 | D10: =IF(B10<=Parametros!$B$17,C10,Parametros!$B$5/(1+Parametros!$B$7*Parametros!$B$6*Parametros!$B$17)^(1/Parametros!$B$7)*EXP(-Parametros!$B$8*(B10-Parametros!$B$17))) -> 696.53657 | E10: =D10*30.4*IF(B10<Parametros!$B$15,1,0) -> 21174.712 | F10: =C10*30.4*IF(B10<Parametros!$B$15,1,0) -> 21174.712 | G10: =(E10*(Parametros!$B$9*(1-Parametros!$B$10)-Parametros!$B$11)-Parametros!$B$12*IF(B10<Parametros!$B$15,1,0))/(1+Parametros!$B$14)^B10 -> 903043.3
A11: 7 | B11: =(A11-1)/12 -> 0.5 | C11: =Parametros!$B$5/(1+Parametros!$B$7*Parametros!$B$6*B11)^(1/Parametros!$B$7) -> 668.38879 | D11: =IF(B11<=Parametros!$B$17,C11,Parametros!$B$5/(1+Parametros!$B$7*Parametros!$B$6*Parametros!$B$17)^(1/Parametros!$B$7)*EXP(-Parametros!$B$8*(B11-Parametros!$B$17))) -> 668.38879 | E11: =D11*30.4*IF(B11<Parametros!$B$15,1,0) -> 20319.019 | F11: =C11*30.4*IF(B11<Parametros!$B$15,1,0) -> 20319.019 | G11: =(E11*(Parametros!$B$9*(1-Parametros!$B$10)-Parametros!$B$11)-Parametros!$B$12*IF(B11<Parametros!$B$15,1,0))/(1+Parametros!$B$14)^B11 -> 859348.26
A12: 8 | B12: =(A12-1)/12 -> 0.58333333 | C12: =Parametros!$B$5/(1+Parametros!$B$7*Parametros!$B$6*B12)^(1/Parametros!$B$7) -> 642.92244 | D12: =IF(B12<=Parametros!$B$17,C12,Parametros!$B$5/(1+Parametros!$B$7*Parametros!$B$6*Parametros!$B$17)^(1/Parametros!$B$7)*EXP(-Parametros!$B$8*(B12-Parametros!$B$17))) -> 642.92244 | E12: =D12*30.4*IF(B12<Parametros!$B$15,1,0) -> 19544.842 | F12: =C12*30.4*IF(B12<Parametros!$B$15,1,0) -> 19544.842 | G12: =(E12*(Parametros!$B$9*(1-Parametros!$B$10)-Parametros!$B$11)-Parametros!$B$12*IF(B12<Parametros!$B$15,1,0))/(1+Parametros!$B$14)^B12 -> 819742.45
A13: 9 | B13: =(A13-1)/12 -> 0.66666667 | C13: =Parametros!$B$5/(1+Parametros!$B$7*Parametros!$B$6*B13)^(1/Parametros!$B$7) -> 619.75087 | D13: =IF(B13<=Parametros!$B$17,C13,Parametros!$B$5/(1+Parametros!$B$7*Parametros!$B$6*Parametros!$B$17)^(1/Parametros!$B$7)*EXP(-Parametros!$B$8*(B13-Parametros!$B$17))) -> 619.75087 | E13: =D13*30.4*IF(B13<Parametros!$B$15,1,0) -> 18840.426 | F13: =C13*30.4*IF(B13<Parametros!$B$15,1,0) -> 18840.426 | G13: =(E13*(Parametros!$B$9*(1-Parametros!$B$10)-Parametros!$B$11)-Parametros!$B$12*IF(B13<Parametros!$B$15,1,0))/(1+Parametros!$B$14)^B13 -> 783642.41
A14: 10 | B14: =(A14-1)/12 -> 0.75 | C14: =Parametros!$B$5/(1+Parametros!$B$7*Parametros!$B$6*B14)^(1/Parametros!$B$7) -> 598.56018 | D14: =IF(B14<=Parametros!$B$17,C14,Parametros!$B$5/(1+Parametros!$B$7*Parametros!$B$6*Parametros!$B$17)^(1/Parametros!$B$7)*EXP(-Parametros!$B$8*(B14-Parametros!$B$17))) -> 598.56018 | E14: =D14*30.4*IF(B14<Parametros!$B$15,1,0) -> 18196.229 | F14: =C14*30.4*IF(B14<Parametros!$B$15,1,0) -> 18196.229 | G14: =(E14*(Parametros!$B$9*(1-Parametros!$B$10)-Parametros!$B$11)-Parametros!$B$12*IF(B14<Parametros!$B$15,1,0))/(1+Parametros!$B$14)^B14 -> 750573.93
A15: 11 | B15: =(A15-1)/12 -> 0.83333333 | C15: =Parametros!$B$5/(1+Parametros!$B$7*Parametros!$B$6*B15)^(1/Parametros!$B$7) -> 579.09263 | D15: =IF(B15<=Parametros!$B$17,C15,Parametros!$B$5/(1+Parametros!$B$7*Parametros!$B$6*Parametros!$B$17)^(1/Parametros!$B$7)*EXP(-Parametros!$B$8*(B15-Parametros!$B$17))) -> 579.09263 | E15: =D15*30.4*IF(B15<Parametros!$B$15,1,0) -> 17604.416 | F15: =C15*30.4*IF(B15<Parametros!$B$15,1,0) -> 17604.416 | G15: =(E15*(Parametros!$B$9*(1-Parametros!$B$10)-Parametros!$B$11)-Parametros!$B$12*IF(B15<Parametros!$B$15,1,0))/(1+Parametros!$B$14)^B15 -> 720147.21
A16: 12 | B16: =(A16-1)/12 -> 0.91666667 | C16: =Parametros!$B$5/(1+Parametros!$B$7*Parametros!$B$6*B16)^(1/Parametros!$B$7) -> 561.13444 | D16: =IF(B16<=Parametros!$B$17,C16,Parametros!$B$5/(1+Parametros!$B$7*Parametros!$B$6*Parametros!$B$17)^(1/Parametros!$B$7)*EXP(-Parametros!$B$8*(B16-Parametros!$B$17))) -> 561.13444 | E16: =D16*30.4*IF(B16<Parametros!$B$15,1,0) -> 17058.487 | F16: =C16*30.4*IF(B16<Parametros!$B$15,1,0) -> 17058.487 | G16: =(E16*(Parametros!$B$9*(1-Parametros!$B$10)-Parametros!$B$11)-Parametros!$B$12*IF(B16<Parametros!$B$15,1,0))/(1+Parametros!$B$14)^B16 -> 692038.59
... A364: 360 | B364: =(A364-1)/12 -> 29.916667 | C364: =Parametros!$B$5/(1+Parametros!$B$7*Parametros!$B$6*B364)^(1/Parametros!$B$7) -> 84.668422 | D364: =IF(B364<=Parametros!$B$17,C364,Parametros!$B$5/(1+Parametros!$B$7*Parametros!$B$6*Parametros!$B$17)^(1/Parametros!$B$7)*EXP(-Parametros!$B$8*(B364-Parametros!$B$17))) -> 51.259912 | E364: =D364*30.4*IF(B364<Parametros!$B$15,1,0) -> 1558.3013 | F364: =C364*30.4*IF(B364<Parametros!$B$15,1,0) -> 2573.92 | G364: =(E364*(Parametros!$B$9*(1-Parametros!$B$10)-Parametros!$B$11)-Parametros!$B$12*IF(B364<Parametros!$B$15,1,0))/(1+Parametros!$B$14)^B364 -> 3512.8322

Sheet Resultados
A1: EUR y valor del pozo
A2: Datos de ejemplo (sintéticos) con fines didácticos. Celdas azules sobre fondo crema = entradas editables; el resto son fórmulas.
A4: Indicador | B4: Valor | C4: Unidad
A5: EUR con declinación terminal | B5: =SUM(Pronostico!E5:E364)/1000 -> 1875.2735 | C5: Mbbl
A6: EUR con hiperbólica pura | B6: =SUM(Pronostico!F5:F364)/1000 -> 1994.0663 | C6: Mbbl
A7: Sobreestimación de la hiperbólica pura | B7: =B6/B5-1 -> 0.063346889
A8: VPN (antes de impuestos) | B8: =(SUM(Pronostico!G5:G364)-Parametros!B13)/1000000 -> 30.228495 | C8: MUSD
A9: Costo de desarrollo (CAPEX / EUR) | B9: =Parametros!B13/(B5*1000) -> 6.932322 | C9: USD/bbl
A11: El VPN se calcula sobre el horizonte elegido, con el mismo método que el laboratorio del curso. Cambiá b y Dmin y mirá el efecto.

Sheet Etapas
A1: Etapas de completación: costo por pie y por etapa (ejemplo)
A2: Datos de ejemplo (sintéticos) con fines didácticos. Celdas azules sobre fondo crema = entradas editables; el resto son fórmulas.
A3: Parámetro
A4: Costo fijo de bombeo por etapa (USD) | B4: 90000
A5: Costo del apuntalante (USD/t) | B5: 230
A6: Costo del fluido (USD/m³) | B6: 14
A7: Costo de cañoneo por clúster (USD) | B7: 9000
A8: Costo del tapón por etapa (USD) | B8: 6000
A10: Etapa | B10: Longitud (m) | C10: Clústeres | D10: Espaciamiento (m) | E10: Apuntalante (t) | F10: Fluido (m³) | G10: Costo de la etapa (USD) | H10: Apuntalante por metro (t/m)
A11: 1 | B11: 60 | C11: 5 | D11: =B11/C11 -> 12 | E11: 202 | F11: 1501 | G11: =$B$4+E11*$B$5+F11*$B$6+C11*$B$7+$B$8 -> 208474 | H11: =E11/B11 -> 3.3666667
A12: 2 | B12: 60 | C12: 4 | D12: =B12/C12 -> 15 | E12: 163 | F12: 1829 | G12: =$B$4+E12*$B$5+F12*$B$6+C12*$B$7+$B$8 -> 195096 | H12: =E12/B12 -> 2.7166667
A13: 3 | B13: 60 | C13: 6 | D13: =B13/C13 -> 10 | E13: 187 | F13: 1660 | G13: =$B$4+E13*$B$5+F13*$B$6+C13*$B$7+$B$8 -> 216250 | H13: =E13/B13 -> 3.1166667
A14: 4 | B14: 70 | C14: 6 | D14: =B14/C14 -> 11.666667 | E14: 210 | F14: 1788 | G14: =$B$4+E14*$B$5+F14*$B$6+C14*$B$7+$B$8 -> 223332 | H14: =E14/B14 -> 3
A15: 5 | B15: 70 | C15: 4 | D15: =B15/C15 -> 17.5 | E15: 209 | F15: 2105 | G15: =$B$4+E15*$B$5+F15*$B$6+C15*$B$7+$B$8 -> 209540 | H15: =E15/B15 -> 2.9857143
A16: 6 | B16: 65 | C16: 6 | D16: =B16/C16 -> 10.833333 | E16: 194 | F16: 2034 | G16: =$B$4+E16*$B$5+F16*$B$6+C16*$B$7+$B$8 -> 223096 | H16: =E16/B16 -> 2.9846154
A17: 7 | B17: 60 | C17: 5 | D17: =B17/C17 -> 12 | E17: 161 | F17: 1831 | G17: =$B$4+E17*$B$5+F17*$B$6+C17*$B$7+$B$8 -> 203664 | H17: =E17/B17 -> 2.6833333
A18: 8 | B18: 70 | C18: 6 | D18: =B18/C18 -> 11.666667 | E18: 188 | F18: 1713 | G18: =$B$4+E18*$B$5+F18*$B$6+C18*$B$7+$B$8 -> 217222 | H18: =E18/B18 -> 2.6857143
A19: 9 | B19: 60 | C19: 4 | D19: =B19/C19 -> 15 | E19: 180 | F19: 1752 | G19: =$B$4+E19*$B$5+F19*$B$6+C19*$B$7+$B$8 -> 197928 | H19: =E19/B19 -> 3
A20: 10 | B20: 60 | C20: 5 | D20: =B20/C20 -> 12 | E20: 185 | F20: 1699 | G20: =$B$4+E20*$B$5+F20*$B$6+C20*$B$7+$B$8 -> 207336 | H20: =E20/B20 -> 3.0833333
A21: 11 | B21: 60 | C21: 6 | D21: =B21/C21 -> 10 | E21: 190 | F21: 1511 | G21: =$B$4+E21*$B$5+F21*$B$6+C21*$B$7+$B$8 -> 214854 | H21: =E21/B21 -> 3.1666667
A22: 12 | B22: 70 | C22: 6 | D22: =B22/C22 -> 11.666667 | E22: 198 | F22: 1880 | G22: =$B$4+E22*$B$5+F22*$B$6+C22*$B$7+$B$8 -> 221860 | H22: =E22/B22 -> 2.8285714
... A46: 36 | B46: 60 | C46: 4 | D46: =B46/C46 -> 15 | E46: 166 | F46: 1442 | G46: =$B$4+E46*$B$5+F46*$B$6+C46*$B$7+$B$8 -> 190368 | H46: =E46/B46 -> 2.7666667
A48: Totales del lateral
A49: Longitud lateral (m) | B49: =SUM(B11:B46) -> 2310
A50: Etapas | B50: =COUNT(A11:A46) -> 36
A51: Costo total de completación (USD) | B51: =SUM(G11:G46) -> 7562040
A52: Costo por metro lateral (USD/m) | B52: =B51/B49 -> 3273.6104
A53: Apuntalante total (t) | B53: =SUM(E11:E46) -> 6815
A54: Espaciamiento medio entre clústeres (m) | B54: =SUM(B11:B46)/SUM(C11:C46) -> 12.622951

Sheet Nolte-Smith
A1: Presión neta de tratamiento y modos de Nolte y Smith (datos sintéticos)
A2: Datos de ejemplo (sintéticos) con fines didácticos. Celdas azules sobre fondo crema = entradas editables; el resto son fórmulas.
A4: Tiempo (min) | B4: Presión neta (psi) | C4: Pendiente log-log | D4: Modo | F4: Modos de Nolte y Smith (clasificación aproximada)
A5: 5 | B5: 900.1 | F5: I: pendiente positiva baja · II: cercana a cero · III: positiva y unitaria · IV: negativa. Los umbrales de la columna D son una guía y se ajustan al ruido de los datos.
A6: 5.4 | B6: 913.3 | C6: =(LN(B6)-LN(B5))/(LN(A6)-LN(A5)) -> 0.18916773 | D6: =IF(C6<-0.05,"IV: altura sin control",IF(C6<0.05,"II: altura o filtrado",IF(C6<0.6,"I: propagación estable","III: restricción, arenamiento"))) -> I: propagación estable
A7: 5.9 | B7: 921.7 | C7: =(LN(B7)-LN(B6))/(LN(A7)-LN(A6)) -> 0.10338821 | D7: =IF(C7<-0.05,"IV: altura sin control",IF(C7<0.05,"II: altura o filtrado",IF(C7<0.6,"I: propagación estable","III: restricción, arenamiento"))) -> I: propagación estable
A8: 6.5 | B8: 936.7 | C8: =(LN(B8)-LN(B7))/(LN(A8)-LN(A7)) -> 0.16668351 | D8: =IF(C8<-0.05,"IV: altura sin control",IF(C8<0.05,"II: altura o filtrado",IF(C8<0.6,"I: propagación estable","III: restricción, arenamiento"))) -> I: propagación estable
A9: 7 | B9: 950.9 | C9: =(LN(B9)-LN(B8))/(LN(A9)-LN(A8)) -> 0.20302599 | D9: =IF(C9<-0.05,"IV: altura sin control",IF(C9<0.05,"II: altura o filtrado",IF(C9<0.6,"I: propagación estable","III: restricción, arenamiento"))) -> I: propagación estable
A10: 7.7 | B10: 961.2 | C10: =(LN(B10)-LN(B9))/(LN(A10)-LN(A9)) -> 0.11303724 | D10: =IF(C10<-0.05,"IV: altura sin control",IF(C10<0.05,"II: altura o filtrado",IF(C10<0.6,"I: propagación estable","III: restricción, arenamiento"))) -> I: propagación estable
A11: 8.4 | B11: 978.1 | C11: =(LN(B11)-LN(B10))/(LN(A11)-LN(A10)) -> 0.20031186 | D11: =IF(C11<-0.05,"IV: altura sin control",IF(C11<0.05,"II: altura o filtrado",IF(C11<0.6,"I: propagación estable","III: restricción, arenamiento"))) -> I: propagación estable
A12: 9.1 | B12: 981.1 | C12: =(LN(B12)-LN(B11))/(LN(A12)-LN(A11)) -> 0.038260536 | D12: =IF(C12<-0.05,"IV: altura sin control",IF(C12<0.05,"II: altura o filtrado",IF(C12<0.6,"I: propagación estable","III: restricción, arenamiento"))) -> II: altura o filtrado
A13: 9.9 | B13: 997.6 | C13: =(LN(B13)-LN(B12))/(LN(A13)-LN(A12)) -> 0.19793419 | D13: =IF(C13<-0.05,"IV: altura sin control",IF(C13<0.05,"II: altura o filtrado",IF(C13<0.6,"I: propagación estable","III: restricción, arenamiento"))) -> I: propagación estable
A14: 10.8 | B14: 1007.4 | C14: =(LN(B14)-LN(B13))/(LN(A14)-LN(A13)) -> 0.11234897 | D14: =IF(C14<-0.05,"IV: altura sin control",IF(C14<0.05,"II: altura o filtrado",IF(C14<0.6,"I: propagación estable","III: restricción, arenamiento"))) -> I: propagación estable
A15: 11.8 | B15: 1020.1 | C15: =(LN(B15)-LN(B14))/(LN(A15)-LN(A14)) -> 0.14147292 | D15: =IF(C15<-0.05,"IV: altura sin control",IF(C15<0.05,"II: altura o filtrado",IF(C15<0.6,"I: propagación estable","III: restricción, arenamiento"))) -> I: propagación estable
A16: 12.8 | B16: 1035.8 | C16: =(LN(B16)-LN(B15))/(LN(A16)-LN(A15)) -> 0.18775946 | D16: =IF(C16<-0.05,"IV: altura sin control",IF(C16<0.05,"II: altura o filtrado",IF(C16<0.6,"I: propagación estable","III: restricción, arenamiento"))) -> I: propagación estable
A17: 14 | B17: 1050.8 | C17: =(LN(B17)-LN(B16))/(LN(A17)-LN(A16)) -> 0.16044367 | D17: =IF(C17<-0.05,"IV: altura sin control",IF(C17<0.05,"II: altura o filtrado",IF(C17<0.6,"I: propagación estable","III: restricción, arenamiento"))) -> I: propagación estable
... A40: 100 | B40: 1877.1 | C40: =(LN(B40)-LN(B39))/(LN(A40)-LN(A39)) -> 1.026332 | D40: =IF(C40<-0.05,"IV: altura sin control",IF(C40<0.05,"II: altura o filtrado",IF(C40<0.6,"I: propagación estable","III: restricción, arenamiento"))) -> III: restricción, arenamiento
